scintegral/__init__.py
scintegral/classifier.py
scintegral/utils.py
scintegral-0.1.3.dist-info/LICENSE
scintegral-0.1.3.dist-info/METADATA
scintegral-0.1.3.dist-info/WHEEL
scintegral-0.1.3.dist-info/top_level.txt
scintegral-0.1.3.dist-info/RECORD
